{
    "device_types": {
        "0x0001": { "name": "ガス漏れセンサ", },
        "0x0002": { "name": "防犯センサ", },
        "0x0003": { "name": "非常センサ", },
        "0x0004": { "name": "救急用センサ", },
        "0x0005": { "name": "地震センサ", },
        "0x0006": { "name": "漏電センサ", },
        "0x0007": { "name": "人体検知センサ", },
        "0x0008": { "name": "来客センサ", },
        "0x0009": { "name": "呼び出しセンサ", },
        "0x000a": { "name": "結露センサ", },
        "0x000b": { "name": "空気汚染センサ", },
        "0x000c": { "name": "酸素センサ", },
        "0x000d": { "name": "照度センサ", },
        "0x000e": { "name": "音センサ", },
        "0x000f": { "name": "投函センサ", },
        "0x0010": { "name": "重荷センサ", },
        "0x0011": { "name": "温度センサ", },
        "0x0012": { "name": "湿度センサ", },
        "0x0013": { "name": "雨センサ", },
        "0x0014": { "name": "水位センサ", },
        "0x0015": { "name": "風呂水位センサ", },
        "0x0016": { "name": "風呂沸き上がりセンサ", },
        "0x0017": { "name": "水漏れセンサ", },
        "0x0018": { "name": "水あふれセンサ", },
        "0x0019": { "name": "火災センサ", },
        "0x001a": { "name": "タバコ煙センサ", },
        "0x001b": { "name": "CO2センサ", },
        "0x001c": { "name": "ガスセンサ", },
        "0x001d": { "name": "VOCセンサ", },
        "0x001e": { "name": "差圧センサ", },
        "0x001f": { "name": "風速センサ", },
        "0x0020": { "name": "臭いセンサ", },
        "0x0021": { "name": "炎センサ", },
        "0x0022": { "name": "電力量センサ", },
        "0x0023": { "name": "電流量センサ", },
        "0x0024": { "name": "昼光センサ", },
        "0x0025": { "name": "水流量センサ", },
        "0x0026": { "name": "微動センサ", },
        "0x0027": { "name": "通貨センサ", },
        "0x0028": { "name": "在床センサ", },
        "0x0029": { "name": "開閉センサ", },
        "0x002a": { "name": "活動量センサ", },
        "0x002b": { "name": "人体位置センサ", },
        "0x002c": { "name": "雪センサ", },
        "0x002d": { "name": "気圧センサ", },
        "0x0130": { "name": "家庭用エアコン", "icon_name": "wind" },
        "0x0131": { "name": "冷風機", },
        "0x0132": { "name": "扇風機", },
        "0x0133": { "name": "換気扇", },
        "0x0134": { "name": "空調換気扇", },
        "0x0135": { "name": "空気清浄機", },
        "0x0136": { "name": "冷風扇", },
        "0x0137": { "name": "サーキュレータ", },
        "0x0138": { "name": "除湿機", },
        "0x0139": { "name": "加湿器", },
        "0x013a": { "name": "天井扇", },
        "0x013b": { "name": "電気こたつ", },
        "0x013c": { "name": "電気あんか", },
        "0x013d": { "name": "電気毛布", },
        "0x013e": { "name": "ストーブ", },
        "0x013f": { "name": "パネルヒータ", },
        "0x0140": { "name": "電気カーペット", },
        "0x0141": { "name": "フロアヒータ", },
        "0x0142": { "name": "電気暖房器", },
        "0x0143": { "name": "ファンヒータ", },
        "0x0144": { "name": "充電器", },
        "0x0145": { "name": "業務用パッケージエアコン室内機", },
        "0x0146": { "name": "業務用パッケージエアコン室外機", },
        "0x0147": { "name": "業務用パッケージエアコン蓄熱ユニット", },
        "0x0148": { "name": "業務用ファンコイルユニット", },
        "0x0149": { "name": "業務用空調冷熱源(チラー)", },
        "0x0150": { "name": "業務用空調温熱源(ボイラー)", },
        "0x0151": { "name": "業務用空調 VAV", },
        "0x0152": { "name": "業務用空調エアハンドリングユニット", },
        "0x0153": { "name": "ユニットクーラー", },
        "0x0154": { "name": "業務用コンデンシングユニット", },
        "0x0155": { "name": "電気蓄熱暖房器", },
        "0x0260": { "name": "電動ブラインド", },
        "0x0261": { "name": "電動シャッター", },
        "0x0262": { "name": "電動カーテン", },
        "0x0263": { "name": "電動雨戸", },
        "0x0264": { "name": "電動ゲート", },
        "0x0265": { "name": "電動窓", },
        "0x0266": { "name": "電動玄関ドア", },
        "0x0267": { "name": "散水器(庭用)", },
        "0x0268": { "name": "散水器(火災用)", },
        "0x0269": { "name": "噴水", },
        "0x026a": { "name": "瞬間湯沸器", },
        "0x026b": { "name": "電気温水器", "icon_name": "Other.water-heater", "icon_rotate": 0 },
        "0x026c": { "name": "太陽熱温水器", },
        "0x026d": { "name": "循環ポンプ", },
        "0x026e": { "name": "電気便座", },
        "0x026f": { "name": "電気錠", },
        "0x0270": { "name": "ガス元弁", },
        "0x0271": { "name": "ホームサウナ", },
        "0x0272": { "name": "瞬間式給湯器", },
        "0x0273": { "name": "浴室暖房乾燥機", },
        "0x0274": { "name": "ホームエレベータ", },
        "0x0275": { "name": "電動間仕切り", },
        "0x0276": { "name": "水平トランスファ", },
        "0x0277": { "name": "電動物干し", },
        "0x0278": { "name": "浄化槽", },
        "0x0279": { "name": "住宅用太陽光発電", "icon_name": "sun.max.fill" },
        "0x027a": { "name": "冷温水熱源機", },
        "0x027b": { "name": "床暖房", },
        "0x027c": { "name": "燃料電池", },
        "0x027d": { "name": "蓄電池", "icon_name": "battery.100", },
        "0x027e": { "name": "電気自動車充放電器", },
        "0x027f": { "name": "エンジンコージェネレーション", },
        "0x0280": { "name": "電力量メータ", },
        "0x0281": { "name": "水力量メータ", },
        "0x0282": { "name": "ガスメータ", },
        "0x0283": { "name": "LPガスメータ", },
        "0x0284": { "name": "時計", },
        "0x0285": { "name": "自動ドア", },
        "0x0286": { "name": "業務用エレベータ", },
        "0x0287": { "name": "分電盤メータリング", },
        "0x0288": { "name": "低圧スマート電力量メータ", "icon_name": "gauge" },
        "0x0289": { "name": "スマートガスメータ", },
        "0x028a": { "name": "高圧スマート電力量メータ", },
        "0x028b": { "name": "灯油メータ", },
        "0x028c": { "name": "スマート灯油メータ", "icon_name": "gauge" },
        "0x0290": { "name": "一般照明", "icon_name": "lightbulb" },
        "0x0291": { "name": "単機能照明", },
        "0x0299": { "name": "非常照明", },
        "0x029d": { "name": "設備照明", },
        "0x02a0": { "name": "ブザー", },
        "0x02a1": { "name": "電気自動車充電器", },
        "0x02a2": { "name": "Household small wind turbine power generation", },
        "0x02a6": { "name": "ハイブリッド給湯器", },
        "0x03b0": { "name": "コーヒーメーカ", },
        "0x03b1": { "name": "コーヒーミル", },
        "0x03b2": { "name": "電気ポット", },
        "0x03b3": { "name": "電気こんろ", },
        "0x03b4": { "name": "トースタ", },
        "0x03b5": { "name": "ジューサ・ミキサ", },
        "0x03b6": { "name": "フードプロセッサ", },
        "0x03b7": { "name": "冷凍冷蔵庫", },
        "0x03b8": { "name": "オーブンレンジ", },
        "0x03b9": { "name": "クッキングヒータ", },
        "0x03ba": { "name": "オーブン", },
        "0x03bb": { "name": "炊飯器", },
        "0x03bc": { "name": "電子ジャー", },
        "0x03bd": { "name": "食器洗い機", },
        "0x03be": { "name": "食器乾燥機", },
        "0x03bf": { "name": "電気もちつき機", },
        "0x03c0": { "name": "保温機", },
        "0x03c1": { "name": "精米機", },
        "0x03c2": { "name": "自動製パン機", },
        "0x03c3": { "name": "スロークッカ", },
        "0x03c4": { "name": "電気漬物機", },
        "0x03c5": { "name": "洗濯機", },
        "0x03c6": { "name": "衣類乾燥機", },
        "0x03c7": { "name": "電気アイロン", },
        "0x03c8": { "name": "ズボンプレッサ", },
        "0x03c9": { "name": "ふとん乾燥機", },
        "0x03ca": { "name": "小物・くつ乾燥機", },
        "0x03cb": { "name": "電気掃除機", },
        "0x03cc": { "name": "ディスポーザ", },
        "0x03cd": { "name": "電気蚊取り機", },
        "0x03ce": { "name": "業務用ショーケース", },
        "0x03cf": { "name": "業務用冷蔵庫", },
        "0x03d0": { "name": "業務用ホットケース", },
        "0x03d1": { "name": "業務用フライヤー", },
        "0x03d2": { "name": "業務用電子レンジ", },
        "0x03d3": { "name": "洗濯乾燥機", },
        "0x03d4": { "name": "業務用ショーケース向け室外機", },
        "0x0401": { "name": "体重計", },
        "0x0402": { "name": "体温計", },
        "0x0403": { "name": "血圧計", },
        "0x0404": { "name": "血糖値計", },
        "0x0405": { "name": "体脂肪計", },
        "0x05fa": { "name": "並列処理併用型電力制御", },
        "0x05fb": { "name": "DRイベントコントローラ", },
        "0x05fc": { "name": "セキュア通信用共有鍵設定ノード", },
        "0x05fd": { "name": "スイッチ", },
        "0x05fe": { "name": "携帯端末", },
        "0x05ff": { "name": "コントローラ", },
        "0x0601": { "name": "ディスプレー", },
        "0x0602": { "name": "テレビ", },
        "0x0603": { "name": "オーディオ", },
        "0x0604": { "name": "ネットワークカメラ", },
        "0x0ef0": { "name": "ノードプロファイル", "icon_name": "n.circle" }
    },
    "properties": {
        "0x0011": {
            "0xe0": {
                "name": "温度計測値",
                "type": "value",
                "class_name" : "PropertyTemperatureSigned2byte"
            }
        },
        "0x0012": {
            "0xe0": {
                "name": "相対湿度計測値",
                "type": "value",
                "class_name" : "PropertyPercent"
            }
        },
        "0x002d": {
            "0xe0": {
                "name": "気圧計測値",
                "type": "value",
                "class_name" : "PropertyPressureUnsigned2byte"
            }
        },
        "0x0290": {
        },
        "0x0279": {
        },
        "0x027d": {
            "0xa0": {
                "name": "AC実効容量(充電)",
                "type": "value",
                "class_name" : "PropertyPowerDigit9"
            },
            "0xa1": {
                "name": "AC実効容量(放電)",
                "type": "value",
                "class_name" : "PropertyPowerDigit9"
            },
            "0xa2": {
                "name": "AC充電可能容量",
                "type": "value",
                "class_name" : "PropertyPowerDigit9"
            },
            "0xa3": {
                "name": "AC放電可能容量",
                "type": "value",
                "class_name" : "PropertyPowerDigit9"
            },
            "0xa4": {
                "name": "AC充電可能量",
                "type": "value",
                "class_name" : "PropertyPowerDigit9"
            },
            "0xa5": {
                "name": "AC放電可能量",
                "type": "value",
                "class_name" : "PropertyPowerDigit9"
            },
            "0xa6": {
                "name": "AC充電上限設定",
                "type": "value",
                "class_name" : "PropertyPercent"
            },
            "0xa7": {
                "name": "AC放電下限設定",
                "type": "value",
                "class_name" : "PropertyPercent"
            },
            "0xa8": {
                "name": "AC積算充電電力量計測値",
                "type": "value",
                "class_name" : "PropertyIntegratedPower"
            },
            "0xa9": {
                "name": "AC積算放電電力量計測値",
                "type": "value",
                "class_name" : "PropertyIntegratedPower"
            },
            "0xaa": {
                "name": "AC充電量設定値",
                "type": "value",
                "class_name" : "PropertyPowerDigit9"
            },
            "0xab": {
                "name": "AC放電量設定値",
                "type": "value",
                "class_name" : "PropertyPowerDigit9"
            },
            "0xc7": {
                "name": "AC定格電力量",
                "type": "value",
                "class_name" : "PropertyPowerDigit9"
            },
            "0xc8": {
                "name": "最小最大充電電力値",
                "type": "value",
                "class_name" : "PropertyPowerMinMax"
            },
            "0xc9": {
                "name": "最小最大放電電力値",
                "type": "value",
                "class_name" : "PropertyPowerMinMax"
            },
            "0xca": {
                "name": "最小最大充電電流値",
                "type": "value",
                "class_name" : "PropertyCurrentMinMax"
            },
            "0xcb": {
                "name": "最小最大放電電流値",
                "type": "value",
                "class_name" : "PropertyCurrentMinMax"
            },
            "0xcc": {
                "name": "再連系許可設定",
                "type": "select",
                "select_items": {
                    "0x41": "許可",
                    "0x42": "禁止",
                },
                "class_name": "PropertySelectable1Byte"
            },
            "0xcd": {
                "name": "運転許可設定",
                "type": "select",
                "select_items": {
                    "0x41": "許可",
                    "0x42": "禁止",
                },
                "class_name": "PropertySelectable1Byte"
            },
            "0xce": {
                "name": "自立運転許可設定",
                "type": "select",
                "select_items": {
                    "0x41": "許可",
                    "0x42": "禁止",
                },
                "class_name": "PropertySelectable1Byte"
            },
            "0xcf": {
                "name": "運転動作状態",
                "type": "select",
                "select_items": {
                    "0x41": "急速充電",
                    "0x42": "充電",
                    "0x43": "放電",
                    "0x44": "待機",
                    "0x45": "テスト",
                    "0x46": "自動",
                    "0x48": "再起動",
                    "0x49": "実効容量再計算処理",
                    "0x40": "その他",
                },
                "class_name": "PropertySelectable1Byte"
            },
            "0xd0": {
                "name": "定格電力量",
                "type": "value",
                "class_name" : "PropertyPowerDigit9"
            },
            "0xd1": {
                "name": "定格容量",
                "type": "value",
                "class_name" : "PropertyCurrentCapacity"
            },
            "0xd2": {
                "name": "定格電圧",
                "type": "value",
                "class_name" : "PropertyVoltage"
            },
            "0xd3": {
                "name": "瞬時充放電電力計測値",
                "type": "value",
                "class_name" : "PropertyInstantPowerSignedDigit9"
            },
            "0xd4": {
                "name": "瞬時充放電電流計測値",
                "type": "value",
                "class_name" : "PropertyInstantCurrentSignedDigit5"
            },
            "0xd5": {
                "name": "瞬時充放電電圧計測値",
                "type": "value",
                "class_name" : "PropertyVoltageSigned"
            },
            "0xd6": {
                "name": "積算放電電力量計測値",
                "type": "value",
                "class_name" : "PropertyIntegratedPower"
            },
            "0xd7": {
                "name": "積算放電電力量リセット設定",
                "type": "value",
            },
            "0xd8": {
                "name": "積算充電電力量計測値",
                "type": "value",
                "class_name" : "PropertyIntegratedPower"
            },
            "0xd9": {
                "name": "積算充電電力量リセット設定",
                "type": "value",
            },
            "0xda": {
                "name": "運転モード設定",
                "type": "select",
                "select_items": {
                    "0x41": "急速充電",
                    "0x42": "充電",
                    "0x43": "放電",
                    "0x44": "待機",
                    "0x45": "テスト",
                    "0x46": "自動",
                    "0x48": "再起動",
                    "0x49": "実効容量再計算処理",
                    "0x40": "その他",
                },
                "class_name": "PropertySelectable1Byte"
            },
            "0xdb": {
                "name": "系統連系状態",
                "type": "select",
                "select_items": {
                    "0x00": "系統連系(逆潮流可)",
                    "0x01": "独立",
                    "0x02": "系統連系(逆潮流不可)",
                },
                "class_name": "PropertySelectable1Byte"
            },
            "0xdc": {
                "name": "最小最大充電電力値(独立時)",
                "type": "value",
                "class_name" : "PropertyPowerMinMax"
            },
            "0xdd": {
                "name": "最小最大放電電力値(独立時)",
                "type": "value",
                "class_name" : "PropertyPowerMinMax"
            },
            "0xde": {
                "name": "最小最大充電電流値(独立時)",
                "type": "value",
                "class_name" : "PropertyCurrentMinMax"
            },
            "0xdf": {
                "name": "最小最大放電電流値(独立時)",
                "type": "value",
                "class_name" : "PropertyCurrentMinMax"
            },
            "0xe0": {
                "name": "充放電量設定値1",
                "type": "value",
                "class_name" : "PropertyPowerSignedDigit9"
            },
            "0xe1": {
                "name": "充放電量設定値2",
                "type": "value",
                "class_name" : "PropertyCurrentSignedCapacity"
            },
            "0xe2": {
                "name": "蓄電残量1",
                "type": "value",
                "class_name" : "PropertyPowerDigit9"
            },
            "0xe3": {
                "name": "蓄電残量2",
                "type": "value",
                "class_name" : "PropertyCurrentCapacity"
            },
            "0xe4": {
                "name": "蓄電残量3",
                "type": "value",
                "class_name" : "PropertyPercent"
            },
            "0xe5": {
                "name": "劣化状態",
                "type": "value",
                "class_name" : "PropertyPercent"
            },
            "0xe6": {
                "name": "蓄電池タイプ",
                "type": "value",
            },
            "0xe7": {
                "name": "充電量設定値1",
                "type": "value",
                "class_name" : "PropertyPowerDigit9"
            },
            "0xe8": {
                "name": "放電量設定値1",
                "type": "value",
                "class_name" : "PropertyPowerDigit9"
            },
            "0xe9": {
                "name": "充電量設定値2",
                "type": "value",
                "class_name" : "PropertyCurrentCapacity"
            },
            "0xea": {
                "name": "放電量設定値2",
                "type": "value",
                "class_name" : "PropertyCurrentCapacity"
            },
            "0xeb": {
                "name": "充電電力設定値",
                "type": "value",
                "class_name" : "PropertyInstantPowerUnsignedDigit9"
            },
            "0xec": {
                "name": "放電電力設定値",
                "type": "value",
                "class_name" : "PropertyInstantPowerUnsignedDigit9"
            },
            "0xed": {
                "name": "充電電流設定値",
                "type": "value",
                "class_name" : "PropertyInstantCurrentUnsignedDigit5"
            },
            "0xee": {
                "name": "放電電流設定値",
                "type": "value",
                "class_name" : "PropertyInstantCurrentUnsignedDigit5"
            },
            "0xef": {
                "name": "定格電圧(独立時)",
                "type": "value",
                "class_name" : "PropertyVoltage"
            }
        },
        "0x026b": {
            "0x90": {
                "name": "ONタイマ予約設定",
                "type": "select",
                "select_items": {
                    "0x41": "予約入",
                    "0x42": "予約切",
                },
                "class_name": "PropertySelectable1Byte"
            },
            "0x91": {
                "name": "ONタイマ時刻設定値",
                "type": "value",
                "class_name": "PropertyHourMinute"
            },
            "0xb0": {
                "name": "湧き上げ自動設定",
                "type": "select",
                "select_items": {
                    "0x41": "自動沸き上げ",
                    "0x42": "手動沸き上げ",
                    "0x43": "手動脇上げ停止",
                },
                "class_name": "PropertySelectable1Byte"
            },
            "0xb1": {
                "name": "湧き上げ湯温自動設定",
                "type": "select",
                "select_items": {
                    "0x41": "AUTO",
                    "0x42": "非AUTO",
                },
                "class_name": "PropertySelectable1Byte"
            },
            "0xb2": {
                "name": "湧き上げ中状態",
                "type": "select",
                "select_items": {
                    "0x41": "沸き上げ中",
                    "0x42": "非沸き上げ中",
                },
                "class_name": "PropertySelectable1Byte"
            },
            "0xb3": {
                "name": "湧き上げ湯温設定値",
                "type": "value",
                "class_name": "PropertyTemperature"
            },
            "0xb4": {
                "name": "手動湧き上げ停止日数設定値",
                "type": "value",
                "class_name": "PropertyDay1Byte"
            },
            "0xb5": {
                "name": "手動湧き上げOFFタイマ相対時間設定値",
                "type": "value",
                "class_name": "PropertyHourMinute"
            },
            "0xb6": {
                "name": "タンク運転モード設定",
                "type": "select",
                "select_items": {
                    "0x41": "標準",
                    "0x42": "節約",
                    "0x43": "多め",
                },
                "class_name": "PropertySelectable1Byte"
            },
            "0xc0": {
                "name": "昼間湧き増し許可設定",
                "type": "select",
                "select_items": {
                    "0x41": "昼間沸き増し許可",
                    "0x42": "昼間沸き増し禁止",
                },
                "class_name": "PropertySelectable1Byte"
            },
            "0xc1": {
                "name": "温水器湯温計測値",
                "type": "value",
                "class_name": "PropertyTemperature"
            },
            "0xc2": {
                "name": "警報発生状態",
                "type": "value"
            },
            "0xc3": {
                "name": "給湯中状態",
                "type": "select",
                "select_items": {
                    "0x41": "給湯中",
                    "0x42": "非給湯中",
                },
                "class_name": "PropertySelectable1Byte"
            },
            "0xc4": {
                "name": "風呂保温運転相対時間設定値",
                "type": "value",
                "class_name": "PropertyHourMinute"
            },
            "0xd1": {
                "name": "給湯温度設定値",
                "type": "value",
                "class_name": "PropertyTemperature"
            },
            "0xd3": {
                "name": "風呂温度設定値",
                "type": "value",
                "class_name": "PropertyTemperature"
            },
            "0xd4": {
                "name": "風呂湯量設定４",
                "type": "value"
            },
            "0xd5": {
                "name": "風呂湯量設定４設定可能最大レベル",
                "type": "value"
            },
            "0xd6": {
                "name": "音量設定値",
                "type": "value",
                "class_name": "PropertyPercent"
            },
            "0xd7": {
                "name": "ミュート設定",
                "type": "select",
                "select_items": {
                    "0x30": "ミュートON",
                    "0x31": "ミュートOFF",
                },
                "class_name": "PropertySelectable1Byte"
            },
            "0xd8": {
                "name": "給湯可能湯量値",
                "type": "value",
                "class_name": "PropertyCapacity2Byte"
            },
            "0xd9": {
                "name": "余剰電力量予測値",
                "type": "value",
            },
            "0xdb": {
                "name": "冬季H/Pユニット定格消費電力",
                "type": "value",
                "class_name": "PropertyInstantPower"
            },
            "0xdc": {
                "name": "中間期H/Pユニット定格消費電力",
                "type": "value",
                "class_name": "PropertyInstantPower"
            },
            "0xdd": {
                "name": "夏季H/Pユニット定格消費電力",
                "type": "value",
                "class_name": "PropertyInstantPower"
            },
            "0xe0": {
                "name": "沸き上げ湯量設定値",
                "type": "value",
                "class_name": "PropertyPercent"
            },
            "0xe1": {
                "name": "残湯量計測値",
                "type": "value",
                "class_name": "PropertyCapacity2Byte"
            },
            "0xe2": {
                "name": "タンク容量値",
                "type": "value",
                "class_name": "PropertyCapacity2Byte"
            },
            "0xe3": {
                "name": "風呂自動モード設定",
                "type": "select",
                "select_items": {
                    "0x41": "自動入",
                    "0x42": "自動解除",
                },
                "class_name": "PropertySelectable1Byte"
            },
            "0xe4": {
                "name": "手動風呂追い焚き動作設定",
                "type": "select",
                "select_items": {
                    "0x41": "追い焚き入",
                    "0x42": "追い焚き切",
                },
                "class_name": "PropertySelectable1Byte"
            },
            "0xe5": {
                "name": "手動風呂足し湯動作設定",
                "type": "select",
                "select_items": {
                    "0x41": "足し湯入",
                    "0x42": "足し湯切",
                },
                "class_name": "PropertySelectable1Byte"
            },
            "0xe6": {
                "name": "手動風呂ぬるめ動作設定",
                "type": "select",
                "select_items": {
                    "0x41": "ぬるめ入",
                    "0x42": "ぬるめ切",
                },
                "class_name": "PropertySelectable1Byte"
            },
            "0xe7": {
                "name": "風呂湯量設定１",
                "type": "value",
                "class_name": "PropertyCapacity1Byte"
            },
            "0xe8": {
                "name": "風呂湯量設定２",
                "type": "value"
            },
            "0xe9": {
                "name": "浴室優先設定",
                "type": "select",
                "select_items": {
                    "0x41": "浴室優先入",
                    "0x42": "浴室優先切",
                },
                "class_name": "PropertySelectable1Byte"
            },
            "0xea": {
                "name": "風呂動作状態監視",
                "type": "select",
                "select_items": {
                    "0x41": "湯張り中",
                    "0x42": "停止中",
                    "0x43": "保温中",
                },
                "class_name": "PropertySelectable1Byte"
            },
            "0xee": {
                "name": "風呂湯量設定３",
                "type": "value",
                "class_name": "PropertyCapacity2Byte"
            },
        },
        "0x0ef0": {
            "0xbf": {
                "name": "個体識別情報",
                "type": "value"
            },
            "0xd3": {
                "name": "自ノードインスタンス数",
                "type": "value"
            },
            "0xd4": {
                "name": "自ノードクラス数",
                "type": "value"
            },
            "0xd5": {
                "name": "インスタンスリスト通知",
                "type": "value"
            },
            "0xd6": {
                "name": "自ノードインスタンスリストS",
                "type": "value"
            },
            "0xd7": {
                "name": "自ノードクラスリストS",
                "type": "value"
            },
        },
        "0x0288": {
            "0xd3": {
                "name": "係数",
                "type": "value"
            },
            "0xd7": {
                "name": "積算電力量有効桁数",
                "type": "value"
            },
            "0xe0": {
                "name": "積算電力量計測値（正方向）",
                "type": "value",
                "class_name": "PropertyEnergy4Byte"
            },
            "0xe1": {
                "name": "積算電力量単位",
                "type": "select",
                "select_items": {
                    "0x00": "1kWh",
                    "0x01": "0.1kWh",
                    "0x02": "0.01kWh",
                    "0x03": "0.001kWh",
                    "0x04": "0.0001kWh",
                    "0x0a": "10kWh",
                    "0x0b": "100kWh",
                    "0x0c": "1000kWh",
                    "0x0d": "10000kWh",
                },
                "class_name": "PropertySelectable1Byte"
            },
            "0xe2": {
                "name": "積算電力量計測値履歴１（正方向）",
                "type": "value"
            },
            "0xe3": {
                "name": "積算電力量計測値（逆方向）",
                "type": "value",
                "class_name": "PropertyEnergy4Byte"
            },
            "0xe4": {
                "name": "積算電力量計測値履歴１（逆方向）",
                "type": "value"
            },
            "0xe5": {
                "name": "積算履歴収集日１",
                "type": "value",
                "class_name": "PropertyDay1Byte"
            },
            "0xe7": {
                "name": "瞬時電力計測値",
                "type": "value",
                "class_name": "PropertyInstantPowerSigned"
            },
            "0xe8": {
                "name": "瞬時電流計測値",
                "type": "value",
                "class_name": "PropertyInstantCurrentSigned"
            },
            "0xea": {
                "name": "定時積算電力量計測値（正方向）",
                "type": "value",
                "class_name": "PropertyEnergyInterval"
            },
            "0xeb": {
                "name": "定時積算電力量計測値（逆方向）",
                "type": "value",
                "class_name": "PropertyEnergyInterval"
            },
            "0xec": {
                "name": "積算電力量計測値履歴２",
                "type": "value"
            },
            "0xed": {
                "name": "積算履歴収集日２",
                "type": "value"
            },
        },
        "0x0130": {
            "0xb0": {
                "name": "運転モード設定",
                "type": "select",
                "select_items": {
                    "0x41": "自動",
                    "0x42": "冷房",
                    "0x43": "暖房",
                    "0x44": "除湿",
                    "0x45": "送風",
                    "0x40": "その他"
                },
                "class_name": "PropertySelectable1Byte"
            },
            "0xb1": {
                "name": "温度自動設定",
                "type": "select",
                "select_items": {
                    "0x41": "AUTO",
                    "0x42": "非AUTO"
                },
                "class_name": "PropertySelectable1Byte"
            },
            "0xb2": {
                "name": "急速動作モード設定",
                "type": "select",
                "select_items": {
                    "0x41": "通常運転",
                    "0x42": "急速",
                    "0x43": "静音"
                },
                "class_name": "PropertySelectable1Byte"
            },
            "0xb3": {
                "name": "温度設定値",
                "type": "value",
                "class_name": "PropertyTemperature"
            },
            "0xb4": {
                "name": "除湿モード時相対湿度設定値",
                "type": "value",
                "class_name": "PropertyPercent"
            },
            "0xb5": {
                "name": "冷房モード時温度設定値",
                "type": "value",
                "class_name": "PropertyTemperature"
            },
            "0xb6": {
                "name": "暖房モード時温度設定値",
                "type": "value",
                "class_name": "PropertyTemperature"
            },
            "0xb7": {
                "name": "除湿モード時温度設定値",
                "type": "value",
                "class_name": "PropertyTemperature"
            },
            "0xb8": {
                "name": "定格消費電力値",
                "type": "value",
                "class_name": "PropertyInstantPower"
            },
            "0xb9": {
                "name": "消費電流計測値",
                "type": "value",
                "class_name": "PropertyInstantCurrent"
            },
            "0xba": {
                "name": "室内相対湿度計測値",
                "type": "value",
                "class_name": "PropertyPercent"
            },
            "0xbb": {
                "name": "室内温度計測値",
                "type": "value",
                "class_name": "PropertyTemperatureSigned"
            },
            "0xbc": {
                "name": "ユーザリモコン温度設定値",
                "type": "value",
                "class_name": "PropertyTemperature"
            },
            "0xbd": {
                "name": "吹き出し温度計測値",
                "type": "value",
                "class_name": "PropertyTemperatureSigned"
            },
            "0xbe": {
                "name": "外気温度計測値",
                "type": "value",
                "class_name": "PropertyTemperatureSigned"
            },
            "0xbf": {
                "name": "相対温度設定値",
                "type": "value",
                "class_name": "PropertyTemperatureSignedPer10"
            },
            "0xa0": {
                "name": "風量設定",
                "type": "select",
                "select_items": {
                    "0x41": "風量自動設定",
                    "0x31": "レベル１",
                    "0x32": "レベル２",
                    "0x33": "レベル３",
                    "0x34": "レベル４",
                    "0x35": "レベル５",
                    "0x36": "レベル６",
                    "0x37": "レベル７",
                    "0x38": "レベル８",
                },
                "class_name": "PropertySelectable1Byte"
            },
            "0xa1": {
                "name": "風向自動設定",
                "type": "select",
                "select_items": {
                    "0x41": "AUTO",
                    "0x42": "非AUTO",
                    "0x43": "上下AUTO",
                    "0x44": "左右AUTO"
                },
                "class_name": "PropertySelectable1Byte"
            },
            "0xa3": {
                "name": "風向スイング設定",
                "type": "select",
                "select_items": {
                    "0x31": "OFF",
                    "0x41": "上下",
                    "0x42": "左右",
                    "0x43": "上下左右"
                },
                "class_name": "PropertySelectable1Byte"
            },
            "0xa4": {
                "name": "風向上下設定",
                "type": "select",
                "select_items": {
                    "0x41": "上",
                    "0x42": "下",
                    "0x43": "中央",
                    "0x44": "上中",
                    "0x45": "下中"
                },
                "class_name": "PropertySelectable1Byte"
            },
            "0xa5": {
                "name": "風向左右設定",
                "type": "select",
                "select_items": {
                    "0x51": "　,　　,　,　　,右",
                    "0x52": "　,　　,　,右中,　",
                    "0x41": "　,　　,　,右中,右",
                    "0x54": "　,　　,中,　　,　",
                    "0x55": "　,　　,中,　　,右",
                    "0x56": "　,　　,中,右中,　",
                    "0x57": "　,　　,中,右中,右",
                    "0x58": "　,左中,　,　　,　",
                    "0x59": "　,左中,　,　　,右",
                    "0x5a": "　,左中,　,右中,　",
                    "0x5b": "　,左中,　,右中,右",
                    "0x5c": "　,左中,中,　　,　",
                    "0x5d": "　,左中,中,　　,右",
                    "0x43": "　,左中,中,右中,　",
                    "0x5f": "　,左中,中,右中,右",
                    "0x60": "左,　　,　,　　,　",
                    "0x61": "左,　　,　,　　,右",
                    "0x62": "左,　　,　,右中,　",
                    "0x63": "左,　　,　,右中,右",
                    "0x64": "左,　　,中,　　,　",
                    "0x65": "左,　　,中,　　,右",
                    "0x66": "左,　　,中,右中,　",
                    "0x67": "左,　　,中,右中,右",
                    "0x42": "左,左中,　,　　,　",
                    "0x69": "左,左中,　,　　,右",
                    "0x6a": "左,左中,　,右中,　",
                    "0x44": "左,左中,　,右中,右",
                    "0x6c": "左,左中,中,　　,　",
                    "0x6d": "左,左中,中,　　,右",
                    "0x6e": "左,左中,中,右中,　",
                    "0x6f": "左,左中,中,右中,右",
                },
                "class_name": "PropertySelectable1Byte"
            },
            "0xaa": {
                "name": "特殊状態",
                "type": "select",
                "select_items": {
                    "0x40": "通常状態",
                    "0x41": "除霜状態",
                    "0x42": "予熱状態",
                    "0x43": "排熱状態"
                },
                "class_name": "PropertySelectable1Byte"
            },
            "0xab": {
                "name": "非優先状態",
                "type": "select",
                "select_items": {
                    "0x40": "通常状態",
                    "0x41": "非優先状態",
                },
                "class_name": "PropertySelectable1Byte"
            },
            "0xc0": {
                "name": "換気モード設定",
                "type": "select",
                "select_items": {
                    "0x41": "換気ON（排気方向）",
                    "0x42": "環境OFF",
                    "0x43": "換気ON（吸気方向）",
                },
                "class_name": "PropertySelectable1Byte"
            },
            "0xc1": {
                "name": "加湿モード設定",
                "type": "select",
                "select_items": {
                    "0x41": "加湿ON",
                    "0x42": "加湿OFF",
                },
                "class_name": "PropertySelectable1Byte"
            },
            "0xc2": {
                "name": "換気風量設定",
                "type": "select",
                "select_items": {
                    "0x41": "換気風量自動",
                    "0x31": "レベル１",
                    "0x32": "レベル２",
                    "0x33": "レベル３",
                    "0x34": "レベル４",
                    "0x35": "レベル５",
                    "0x36": "レベル６",
                    "0x37": "レベル７",
                    "0x38": "レベル８",
                },
                "class_name": "PropertySelectable1Byte"
            },
            "0xc4": {
                "name": "加湿量設定",
                "type": "select",
                "select_items": {
                    "0x41": "加湿量自動",
                    "0x31": "レベル１",
                    "0x32": "レベル２",
                    "0x33": "レベル３",
                    "0x34": "レベル４",
                    "0x35": "レベル５",
                    "0x36": "レベル６",
                    "0x37": "レベル７",
                    "0x38": "レベル８",
                },
                "class_name": "PropertySelectable1Byte"
            },
            "0xc6": {
                "name": "搭載空気清浄方法",
                "type": "value"
            },
            "0xc7": {
                "name": "空気清浄機能モード設定",
                "type": "value"
            },
            "0xc8": {
                "name": "搭載リフレッシュ方法",
                "type": "value"
            },
            "0xc9": {
                "name": "リフレッシュ機能モード設定",
                "type": "value"
            },
            "0xca": {
                "name": "搭載自己洗浄方法",
                "type": "value"
            },
            "0xcb": {
                "name": "自己洗浄機能モード設定",
                "type": "value"
            },
            "0xcc": {
                "name": "特別運転モード設定",
                "type": "select",
                "select_items": {
                    "0x40": "設定なし",
                    "0x41": "衣類乾燥",
                    "0x42": "結露抑制",
                    "0x43": "ダニカビ抑制",
                    "0x44": "強制除霜",
                },
                "class_name": "PropertySelectable1Byte"
            },
            "0xcd": {
                "name": "内部動作状態",
                "type": "value"
            },
            "0xce": {
                "name": "強制サーモモード設定",
                "type": "select",
                "select_items": {
                    "0x40": "通常設定",
                    "0x41": "強制サーモON",
                    "0x42": "強制サーモOFF",
                },
                "class_name": "PropertySelectable1Byte"
            },
            "0xcf": {
                "name": "空気清浄モード設定",
                "type": "select",
                "select_items": {
                    "0x41": "空気清浄ON",
                    "0x42": "空気清浄OFF",
                },
                "class_name": "PropertySelectable1Byte"
            },
            "0xd0": {
                "name": "ブザー",
                "type": "select",
                "select_items": {
                    "0x41": "ブザー音発生",
                },
                "class_name": "PropertySelectable1Byte"
            },
            "0x90": {
                "name": "ONタイマ予約設定",
                "type": "select",
                "select_items": {
                    "0x41": "予約入",
                    "0x42": "予約切",
                    "0x43": "時刻予約のみ入",
                    "0x44": "相対時刻予約のみ入",
                },
                "class_name": "PropertySelectable1Byte"
            },
            "0x91": {
                "name": "ONタイマ時刻設定値",
                "type": "value",
                "class_name": "PropertyHourMinute"
            },
            "0x92": {
                "name": "ONタイマ相対時間設定値",
                "type": "value",
                "class_name": "PropertyHourMinute"
            },
            "0x94": {
                "name": "OFFタイマ予約設定",
                "type": "select",
                "select_items": {
                    "0x41": "予約入",
                    "0x42": "予約切",
                    "0x43": "時刻予約のみ入",
                    "0x44": "相対時刻予約のみ入",
                },
                "class_name": "PropertySelectable1Byte"
            },
            "0x95": {
                "name": "OFFタイマ時刻設定値",
                "type": "value",
                "class_name": "PropertyHourMinute"
            },
            "0x96": {
                "name": "OFFタイマ相対時間設定値",
                "type": "value",
                "class_name": "PropertyHourMinute"
            },
        },
        "super": {
            "0x80": {
                "name": "動作状態",
                "type": "select",
                "select_items": {
                    "0x30": "ON",
                    "0x31": "OFF"
                },
                "class_name": "PropertySelectable1Byte"
            },
            "0x81": {
                "name": "設置場所",
                "type": "select",
                "select_items": {
                    "0x00": "設置場所未設定",
                    "0x01": "位置情報定義",
                    "0x08": "居間、リビング",
                    "0x10": "食堂、ダイニング",
                    "0x18": "台所、キッチン",
                    "0x20": "浴室、バス",
                    "0x28": "トイレ",
                    "0x30": "洗面所、脱衣所",
                    "0x38": "廊下",
                    "0x40": "部屋",
                    "0x48": "階段",
                    "0x50": "玄関",
                    "0x58": "納戸",
                    "0x60": "庭、外周",
                    "0x68": "車庫",
                    "0x70": "ベランダ、バルコニー",
                    "0x78": "その他",
                    "0x80": "unknown",
                    "0xff": "設置場所不定"
                },
                "class_name": "PropertySelectableLocation"
            },
            "0x82": {
                "name": "規格Version情報",
                "type": "value"
            },
            "0x83": {
                "name": "識別番号",
                "type": "value"
            },
            "0x84": {
                "name": "瞬時消費電力計測値",
                "type": "value",
                "class_name": "PropertyInstantPower"
            },
            "0x85": {
                "name": "積算消費電力計測値",
                "type": "value",
                "class_name": "PropertyIntegratedPower"
            },
            "0x86": {
                "name": "メーカ異常コード",
                "type": "value"
            },
            "0x87": {
                "name": "電流制限設定",
                "type": "value"
            },
            "0x88": {
                "name": "異常発生状態",
                "type": "value",
                "select_items": {
                    "0x41": "異常発生有",
                    "0x42": "異常発生無"
                },
                "class_name": "PropertySelectable1Byte"
            },
            "0x89": {
                "name": "異常内容",
                "type": "value"
            },
            "0x8a": {
                "name": "メーカコード",
                "type": "select",
                "select_items": {
                    "0x000005": "シャープ株式会社",
                    "0x000006": "三菱電機株式会社",
                    "0x000008": "ダイキン工業株式会社",
                    "0x000009": "日本電気株式会社",
                    "0x00000b": "パナソニック株式会社",
                    "0x000016": "株式会社東芝",
                    "0x00001b": "東芝ライテック株式会社",
                    "0x000022": "日立アプライアンス株式会社",
                    "0x00004e": "富士通株式会社",
                    "0x000053": "株式会社ユビキタス",
                    "0x000059": "リンナイ株式会社",
                    "0x00005e": "株式会社gwソーラー",
                    "0x000060": "株式会社ソニーコンピュータサイエンス研究所",
                    "0x000063": "河村電器産業株式会社",
                    "0x000064": "オムロン株式会社",
                    "0x000069": "東芝ライフスタイル株式会社",
                    "0x00006c": "ニチコン株式会社",
                    "0x00006f": "株式会社バッファロー",
                    "0x000072": "株式会社エナリス",
                    "0x000077": "神奈川工科大学",
                    "0x000078": "日立マクセル株式会社",
                    "0x00007d": "powertech industrial",
                    "0x000086": "西日本電信電話株式会社",
                    "0x00008a": "株式会社富士通ゼネラル",
                    "0x0000a3": "中部電力株式会社",
                    "0x0000aa": "株式会社テンフィートライト",
                    "0x0000ae": "四国電力株式会社",
                    "0x0000b5": "中国電力株式会社",
                    "0x0000b6": "文化シヤッター株式会社",
                    "0x0000b8": "北海道電力株式会社",
                },
                "class_name": "PropertySelectable3Byte"
            },
            "0x8b": {
                "name": "事業場コード",
                "type": "value"
            },
            "0x8c": {
                "name": "商品コード",
                "type": "value"
            },
            "0x8d": {
                "name": "製造番号",
                "type": "value"
            },
            "0x8e": {
                "name": "製造年月日",
                "type": "value"
            },
            "0x8f": {
                "name": "節電動作設定",
                "type": "value",
                "select_items": {
                    "0x41": "節電動作中",
                    "0x42": "通常動作中"
                },
                "class_name": "PropertySelectable1Byte"
            },
            "0x93": {
                "name": "遠隔操作設定",
                "type": "value",
                "select_items": {
                    "0x41": "公衆回線未経由操作",
                    "0x42": "公衆回線経由操作",
                    "0x61": "通信回線正常（操作不可）",
                    "0x62": "通信回線正常（操作可能）"
                },
                "class_name": "PropertySelectable1Byte"
            },
            "0x97": {
                "name": "現在時刻設定",
                "type": "value",
                "class_name": "PropertyHourMinute"
            },
            "0x98": {
                "name": "現在年月日設定",
                "type": "value",
                "class_name": "PropertyYearMonthDay"
            },
            "0x99": {
                "name": "電力制限設定",
                "type": "value",
                "class_name": "PropertyInstantPower"
            },
            "0x9a": {
                "name": "積算運転時間",
                "type": "value",
                "class_name": "PropertyTotalOperatingTime"
            },
            "0x9b": {
                "name": "SetMプロパティマップ",
                "type": "value"
            },
            "0x9c": {
                "name": "GetMプロパティマップ",
                "type": "value"
            },
            "0x9d": {
                "name": "状変プロパティマップ",
                "type": "value"
            },
            "0x9e": {
                "name": "Setプロパティマップ",
                "type": "value"
            },
            "0x9f": {
                "name": "Getプロパティマップ",
                "type": "value"
            },
        }
    }
}
